Smg88/__import__.py
Smg88/__init__.py
Smg88/__interface__.py
Smg88/__main__.py
Smg88/coms.py
Smg88/easycopyforAndrew.py
Smg88/errors.py
Smg88/events.py
Smg88/hashing.py
Smg88/loghelp.py
Smg88/morgan.py
Smg88/py.typed
Smg88/ryanpinger.py
Smg88/security.py
Smg88/typehelp.py
Smg88_Testing/__init__.py
Smg88_Testing/py.typed
Smg88_Testing/test_EventStage.py
Smg88-0.3.14.dist-info/LICENSE
Smg88-0.3.14.dist-info/METADATA
Smg88-0.3.14.dist-info/WHEEL
Smg88-0.3.14.dist-info/top_level.txt
Smg88-0.3.14.dist-info/RECORD
